py4hw/__init__.py
py4hw/base.py
py4hw/code_generation.py
py4hw/debug.py
py4hw/gui.py
py4hw/helper.py
py4hw/py4hw_generation.py
py4hw/rtl_generation.py
py4hw/schematic.py
py4hw/schematic_symbols.py
py4hw/simulation.py
py4hw/zoomin24.png
py4hw/zoomout24.png
py4hw/external/__init__.py
py4hw/external/altera/__init__.py
py4hw/external/altera/ip/PerformanceCounter.py
py4hw/external/altera/ip/__init__.py
py4hw/external/altera/ip/cycloneiii.py
py4hw/external/intel/BlockDesignFile.py
py4hw/external/intel/VectorWaveformFile.py
py4hw/external/intel/__init__.py
py4hw/external/intel/ip/__init__.py
py4hw/external/intel/ip/alt.py
py4hw/external/intel/ip/lpm.py
py4hw/external/platforms/__init__.py
py4hw/external/platforms/intel.py
py4hw/external/platforms/terasic.py
py4hw/external/platforms/xilinx.py
py4hw/external/xilinx/__init__.py
py4hw/external/xilinx/ip/__init__.py
py4hw/external/xilinx/ip/xpm.py
py4hw/logic/__init__.py
py4hw/logic/arithmetic.py
py4hw/logic/arithmetic_fp.py
py4hw/logic/arithmetic_fxp.py
py4hw/logic/bitwise.py
py4hw/logic/clock.py
py4hw/logic/relational.py
py4hw/logic/simulation.py
py4hw/logic/storage.py
py4hw/transpilation/__init__.py
py4hw/transpilation/ast2src.py
py4hw/transpilation/ast2xml.py
py4hw/transpilation/astutils.py
py4hw/transpilation/hls_timed.py
py4hw/transpilation/python2cflexhdl_transpilation.py
py4hw/transpilation/python2structural.py
py4hw/transpilation/python2verilog_transpilation.py
py4hw-2025.5.dist-info/licenses/LICENSE
py4hw-2025.5.dist-info/METADATA
py4hw-2025.5.dist-info/WHEEL
py4hw-2025.5.dist-info/top_level.txt
py4hw-2025.5.dist-info/RECORD
