Metadata-Version: 2.4
Name: py4hw
Version: 2025.5
Summary: py4hw is a library to model, and simulate digital logic circuits. It promotes the use of structural and behavioural design styles to build hardware.
Home-page: https://github.com/davidcastells/py4hw
Author: David Castells-Rufas
Author-email: david.castells@uab.cat
License-File: LICENSE
Requires-Dist: nbwavedrom==0.2.0
Requires-Dist: ipywidgets
Requires-Dist: matplotlib
Requires-Dist: deprecated
Requires-Dist: pytest
Requires-Dist: edalize
Requires-Dist: setuptools
Requires-Dist: astunparse
Dynamic: author
Dynamic: author-email
Dynamic: description
Dynamic: description-content-type
Dynamic: home-page
Dynamic: license-file
Dynamic: requires-dist
Dynamic: summary
